{
  "schemaVersion": 1,
  "generatedAt": "2026-06-26T08:10:14.789979+02:00",
  "timezone": "Europe/Prague",
  "dataRange": {
    "firstRecordAt": "2025-06-23T06:00:00+02:00",
    "lastRecordAt": "2026-06-26T08:00:00+02:00"
  },
  "poolName": "Aquapark Kohoutovice",
  "currentOccupancy": {
    "occupancy": 43,
    "time": "08:10",
    "timestamp": "2026-06-26T08:10:00+02:00",
    "currentUtilizationRate": 14,
    "averageUtilizationRate": 14,
    "maximumCapacity": 298,
    "totalLanes": null,
    "openLanes": null
  },
  "overallOccupancyMap": {
    "maxOverallValues": {
      "averageUtilizationRate": 57,
      "weightedAverageUtilizationRate": 57,
      "medianUtilizationRate": 56
    },
    "days": {
      "Monday": {
        "maxDayValues": {
          "averageUtilizationRate": 47,
          "weightedAverageUtilizationRate": 48,
          "medianUtilizationRate": 49
        },
        "hours": {
          "6": {
            "averageUtilizationRate": 7,
            "weightedAverageUtilizationRate": 8,
            "medianUtilizationRate": 7
          },
          "7": {
            "averageUtilizationRate": 11,
            "weightedAverageUtilizationRate": 12,
            "medianUtilizationRate": 11
          },
          "8": {
            "averageUtilizationRate": 14,
            "weightedAverageUtilizationRate": 15,
            "medianUtilizationRate": 15
          },
          "9": {
            "averageUtilizationRate": 14,
            "weightedAverageUtilizationRate": 15,
            "medianUtilizationRate": 13
          },
          "10": {
            "averageUtilizationRate": 17,
            "weightedAverageUtilizationRate": 18,
            "medianUtilizationRate": 13
          },
          "11": {
            "averageUtilizationRate": 20,
            "weightedAverageUtilizationRate": 21,
            "medianUtilizationRate": 15
          },
          "12": {
            "averageUtilizationRate": 18,
            "weightedAverageUtilizationRate": 19,
            "medianUtilizationRate": 15
          },
          "13": {
            "averageUtilizationRate": 17,
            "weightedAverageUtilizationRate": 19,
            "medianUtilizationRate": 15
          },
          "14": {
            "averageUtilizationRate": 22,
            "weightedAverageUtilizationRate": 23,
            "medianUtilizationRate": 19
          },
          "15": {
            "averageUtilizationRate": 32,
            "weightedAverageUtilizationRate": 33,
            "medianUtilizationRate": 30
          },
          "16": {
            "averageUtilizationRate": 40,
            "weightedAverageUtilizationRate": 40,
            "medianUtilizationRate": 37
          },
          "17": {
            "averageUtilizationRate": 47,
            "weightedAverageUtilizationRate": 48,
            "medianUtilizationRate": 49
          },
          "18": {
            "averageUtilizationRate": 47,
            "weightedAverageUtilizationRate": 48,
            "medianUtilizationRate": 48
          },
          "19": {
            "averageUtilizationRate": 31,
            "weightedAverageUtilizationRate": 32,
            "medianUtilizationRate": 32
          },
          "20": {
            "averageUtilizationRate": 20,
            "weightedAverageUtilizationRate": 20,
            "medianUtilizationRate": 20
          },
          "21": {
            "averageUtilizationRate": 9,
            "weightedAverageUtilizationRate": 10,
            "medianUtilizationRate": 7
          }
        }
      },
      "Tuesday": {
        "maxDayValues": {
          "averageUtilizationRate": 47,
          "weightedAverageUtilizationRate": 48,
          "medianUtilizationRate": 46
        },
        "hours": {
          "6": {
            "averageUtilizationRate": 7,
            "weightedAverageUtilizationRate": 7,
            "medianUtilizationRate": 7
          },
          "7": {
            "averageUtilizationRate": 10,
            "weightedAverageUtilizationRate": 11,
            "medianUtilizationRate": 10
          },
          "8": {
            "averageUtilizationRate": 12,
            "weightedAverageUtilizationRate": 13,
            "medianUtilizationRate": 12
          },
          "9": {
            "averageUtilizationRate": 13,
            "weightedAverageUtilizationRate": 14,
            "medianUtilizationRate": 11
          },
          "10": {
            "averageUtilizationRate": 17,
            "weightedAverageUtilizationRate": 18,
            "medianUtilizationRate": 13
          },
          "11": {
            "averageUtilizationRate": 19,
            "weightedAverageUtilizationRate": 21,
            "medianUtilizationRate": 14
          },
          "12": {
            "averageUtilizationRate": 18,
            "weightedAverageUtilizationRate": 19,
            "medianUtilizationRate": 15
          },
          "13": {
            "averageUtilizationRate": 17,
            "weightedAverageUtilizationRate": 18,
            "medianUtilizationRate": 15
          },
          "14": {
            "averageUtilizationRate": 22,
            "weightedAverageUtilizationRate": 23,
            "medianUtilizationRate": 21
          },
          "15": {
            "averageUtilizationRate": 34,
            "weightedAverageUtilizationRate": 34,
            "medianUtilizationRate": 33
          },
          "16": {
            "averageUtilizationRate": 41,
            "weightedAverageUtilizationRate": 42,
            "medianUtilizationRate": 40
          },
          "17": {
            "averageUtilizationRate": 47,
            "weightedAverageUtilizationRate": 48,
            "medianUtilizationRate": 46
          },
          "18": {
            "averageUtilizationRate": 44,
            "weightedAverageUtilizationRate": 45,
            "medianUtilizationRate": 45
          },
          "19": {
            "averageUtilizationRate": 31,
            "weightedAverageUtilizationRate": 32,
            "medianUtilizationRate": 31
          },
          "20": {
            "averageUtilizationRate": 21,
            "weightedAverageUtilizationRate": 21,
            "medianUtilizationRate": 22
          },
          "21": {
            "averageUtilizationRate": 9,
            "weightedAverageUtilizationRate": 11,
            "medianUtilizationRate": 8
          }
        }
      },
      "Wednesday": {
        "maxDayValues": {
          "averageUtilizationRate": 50,
          "weightedAverageUtilizationRate": 52,
          "medianUtilizationRate": 52
        },
        "hours": {
          "6": {
            "averageUtilizationRate": 9,
            "weightedAverageUtilizationRate": 10,
            "medianUtilizationRate": 9
          },
          "7": {
            "averageUtilizationRate": 11,
            "weightedAverageUtilizationRate": 12,
            "medianUtilizationRate": 12
          },
          "8": {
            "averageUtilizationRate": 16,
            "weightedAverageUtilizationRate": 17,
            "medianUtilizationRate": 16
          },
          "9": {
            "averageUtilizationRate": 15,
            "weightedAverageUtilizationRate": 16,
            "medianUtilizationRate": 14
          },
          "10": {
            "averageUtilizationRate": 17,
            "weightedAverageUtilizationRate": 18,
            "medianUtilizationRate": 14
          },
          "11": {
            "averageUtilizationRate": 18,
            "weightedAverageUtilizationRate": 19,
            "medianUtilizationRate": 13
          },
          "12": {
            "averageUtilizationRate": 18,
            "weightedAverageUtilizationRate": 20,
            "medianUtilizationRate": 15
          },
          "13": {
            "averageUtilizationRate": 17,
            "weightedAverageUtilizationRate": 18,
            "medianUtilizationRate": 14
          },
          "14": {
            "averageUtilizationRate": 21,
            "weightedAverageUtilizationRate": 22,
            "medianUtilizationRate": 19
          },
          "15": {
            "averageUtilizationRate": 28,
            "weightedAverageUtilizationRate": 29,
            "medianUtilizationRate": 27
          },
          "16": {
            "averageUtilizationRate": 41,
            "weightedAverageUtilizationRate": 43,
            "medianUtilizationRate": 43
          },
          "17": {
            "averageUtilizationRate": 50,
            "weightedAverageUtilizationRate": 52,
            "medianUtilizationRate": 52
          },
          "18": {
            "averageUtilizationRate": 43,
            "weightedAverageUtilizationRate": 46,
            "medianUtilizationRate": 46
          },
          "19": {
            "averageUtilizationRate": 32,
            "weightedAverageUtilizationRate": 34,
            "medianUtilizationRate": 32
          },
          "20": {
            "averageUtilizationRate": 22,
            "weightedAverageUtilizationRate": 23,
            "medianUtilizationRate": 23
          },
          "21": {
            "averageUtilizationRate": 8,
            "weightedAverageUtilizationRate": 11,
            "medianUtilizationRate": 7
          }
        }
      },
      "Thursday": {
        "maxDayValues": {
          "averageUtilizationRate": 51,
          "weightedAverageUtilizationRate": 51,
          "medianUtilizationRate": 52
        },
        "hours": {
          "6": {
            "averageUtilizationRate": 8,
            "weightedAverageUtilizationRate": 9,
            "medianUtilizationRate": 8
          },
          "7": {
            "averageUtilizationRate": 10,
            "weightedAverageUtilizationRate": 12,
            "medianUtilizationRate": 11
          },
          "8": {
            "averageUtilizationRate": 12,
            "weightedAverageUtilizationRate": 13,
            "medianUtilizationRate": 12
          },
          "9": {
            "averageUtilizationRate": 13,
            "weightedAverageUtilizationRate": 14,
            "medianUtilizationRate": 13
          },
          "10": {
            "averageUtilizationRate": 16,
            "weightedAverageUtilizationRate": 17,
            "medianUtilizationRate": 15
          },
          "11": {
            "averageUtilizationRate": 17,
            "weightedAverageUtilizationRate": 18,
            "medianUtilizationRate": 14
          },
          "12": {
            "averageUtilizationRate": 18,
            "weightedAverageUtilizationRate": 18,
            "medianUtilizationRate": 15
          },
          "13": {
            "averageUtilizationRate": 20,
            "weightedAverageUtilizationRate": 20,
            "medianUtilizationRate": 17
          },
          "14": {
            "averageUtilizationRate": 23,
            "weightedAverageUtilizationRate": 23,
            "medianUtilizationRate": 20
          },
          "15": {
            "averageUtilizationRate": 34,
            "weightedAverageUtilizationRate": 34,
            "medianUtilizationRate": 32
          },
          "16": {
            "averageUtilizationRate": 46,
            "weightedAverageUtilizationRate": 46,
            "medianUtilizationRate": 46
          },
          "17": {
            "averageUtilizationRate": 51,
            "weightedAverageUtilizationRate": 51,
            "medianUtilizationRate": 52
          },
          "18": {
            "averageUtilizationRate": 47,
            "weightedAverageUtilizationRate": 47,
            "medianUtilizationRate": 47
          },
          "19": {
            "averageUtilizationRate": 34,
            "weightedAverageUtilizationRate": 34,
            "medianUtilizationRate": 34
          },
          "20": {
            "averageUtilizationRate": 22,
            "weightedAverageUtilizationRate": 23,
            "medianUtilizationRate": 23
          },
          "21": {
            "averageUtilizationRate": 9,
            "weightedAverageUtilizationRate": 10,
            "medianUtilizationRate": 9
          },
          "22": {
            "averageUtilizationRate": 1,
            "weightedAverageUtilizationRate": 1,
            "medianUtilizationRate": 1
          }
        }
      },
      "Friday": {
        "maxDayValues": {
          "averageUtilizationRate": 48,
          "weightedAverageUtilizationRate": 48,
          "medianUtilizationRate": 47
        },
        "hours": {
          "6": {
            "averageUtilizationRate": 8,
            "weightedAverageUtilizationRate": 9,
            "medianUtilizationRate": 8
          },
          "7": {
            "averageUtilizationRate": 12,
            "weightedAverageUtilizationRate": 13,
            "medianUtilizationRate": 12
          },
          "8": {
            "averageUtilizationRate": 14,
            "weightedAverageUtilizationRate": 15,
            "medianUtilizationRate": 15
          },
          "9": {
            "averageUtilizationRate": 15,
            "weightedAverageUtilizationRate": 16,
            "medianUtilizationRate": 14
          },
          "10": {
            "averageUtilizationRate": 20,
            "weightedAverageUtilizationRate": 21,
            "medianUtilizationRate": 17
          },
          "11": {
            "averageUtilizationRate": 22,
            "weightedAverageUtilizationRate": 22,
            "medianUtilizationRate": 17
          },
          "12": {
            "averageUtilizationRate": 20,
            "weightedAverageUtilizationRate": 20,
            "medianUtilizationRate": 17
          },
          "13": {
            "averageUtilizationRate": 20,
            "weightedAverageUtilizationRate": 20,
            "medianUtilizationRate": 19
          },
          "14": {
            "averageUtilizationRate": 25,
            "weightedAverageUtilizationRate": 25,
            "medianUtilizationRate": 24
          },
          "15": {
            "averageUtilizationRate": 37,
            "weightedAverageUtilizationRate": 37,
            "medianUtilizationRate": 36
          },
          "16": {
            "averageUtilizationRate": 46,
            "weightedAverageUtilizationRate": 46,
            "medianUtilizationRate": 46
          },
          "17": {
            "averageUtilizationRate": 48,
            "weightedAverageUtilizationRate": 48,
            "medianUtilizationRate": 47
          },
          "18": {
            "averageUtilizationRate": 37,
            "weightedAverageUtilizationRate": 37,
            "medianUtilizationRate": 35
          },
          "19": {
            "averageUtilizationRate": 27,
            "weightedAverageUtilizationRate": 27,
            "medianUtilizationRate": 26
          },
          "20": {
            "averageUtilizationRate": 23,
            "weightedAverageUtilizationRate": 24,
            "medianUtilizationRate": 23
          },
          "21": {
            "averageUtilizationRate": 10,
            "weightedAverageUtilizationRate": 12,
            "medianUtilizationRate": 9
          }
        }
      },
      "Saturday": {
        "maxDayValues": {
          "averageUtilizationRate": 52,
          "weightedAverageUtilizationRate": 53,
          "medianUtilizationRate": 52
        },
        "hours": {
          "8": {
            "averageUtilizationRate": 11,
            "weightedAverageUtilizationRate": 12,
            "medianUtilizationRate": 10
          },
          "9": {
            "averageUtilizationRate": 23,
            "weightedAverageUtilizationRate": 24,
            "medianUtilizationRate": 21
          },
          "10": {
            "averageUtilizationRate": 35,
            "weightedAverageUtilizationRate": 36,
            "medianUtilizationRate": 34
          },
          "11": {
            "averageUtilizationRate": 37,
            "weightedAverageUtilizationRate": 38,
            "medianUtilizationRate": 35
          },
          "12": {
            "averageUtilizationRate": 33,
            "weightedAverageUtilizationRate": 34,
            "medianUtilizationRate": 31
          },
          "13": {
            "averageUtilizationRate": 32,
            "weightedAverageUtilizationRate": 32,
            "medianUtilizationRate": 29
          },
          "14": {
            "averageUtilizationRate": 39,
            "weightedAverageUtilizationRate": 40,
            "medianUtilizationRate": 38
          },
          "15": {
            "averageUtilizationRate": 50,
            "weightedAverageUtilizationRate": 51,
            "medianUtilizationRate": 49
          },
          "16": {
            "averageUtilizationRate": 52,
            "weightedAverageUtilizationRate": 53,
            "medianUtilizationRate": 52
          },
          "17": {
            "averageUtilizationRate": 47,
            "weightedAverageUtilizationRate": 48,
            "medianUtilizationRate": 44
          },
          "18": {
            "averageUtilizationRate": 41,
            "weightedAverageUtilizationRate": 42,
            "medianUtilizationRate": 41
          },
          "19": {
            "averageUtilizationRate": 31,
            "weightedAverageUtilizationRate": 32,
            "medianUtilizationRate": 33
          },
          "20": {
            "averageUtilizationRate": 23,
            "weightedAverageUtilizationRate": 24,
            "medianUtilizationRate": 23
          },
          "21": {
            "averageUtilizationRate": 9,
            "weightedAverageUtilizationRate": 10,
            "medianUtilizationRate": 8
          }
        }
      },
      "Sunday": {
        "maxDayValues": {
          "averageUtilizationRate": 57,
          "weightedAverageUtilizationRate": 57,
          "medianUtilizationRate": 56
        },
        "hours": {
          "8": {
            "averageUtilizationRate": 13,
            "weightedAverageUtilizationRate": 14,
            "medianUtilizationRate": 13
          },
          "9": {
            "averageUtilizationRate": 28,
            "weightedAverageUtilizationRate": 28,
            "medianUtilizationRate": 27
          },
          "10": {
            "averageUtilizationRate": 43,
            "weightedAverageUtilizationRate": 43,
            "medianUtilizationRate": 43
          },
          "11": {
            "averageUtilizationRate": 47,
            "weightedAverageUtilizationRate": 47,
            "medianUtilizationRate": 44
          },
          "12": {
            "averageUtilizationRate": 40,
            "weightedAverageUtilizationRate": 40,
            "medianUtilizationRate": 38
          },
          "13": {
            "averageUtilizationRate": 37,
            "weightedAverageUtilizationRate": 37,
            "medianUtilizationRate": 36
          },
          "14": {
            "averageUtilizationRate": 47,
            "weightedAverageUtilizationRate": 47,
            "medianUtilizationRate": 44
          },
          "15": {
            "averageUtilizationRate": 57,
            "weightedAverageUtilizationRate": 57,
            "medianUtilizationRate": 56
          },
          "16": {
            "averageUtilizationRate": 57,
            "weightedAverageUtilizationRate": 57,
            "medianUtilizationRate": 56
          },
          "17": {
            "averageUtilizationRate": 51,
            "weightedAverageUtilizationRate": 51,
            "medianUtilizationRate": 51
          },
          "18": {
            "averageUtilizationRate": 41,
            "weightedAverageUtilizationRate": 41,
            "medianUtilizationRate": 40
          },
          "19": {
            "averageUtilizationRate": 29,
            "weightedAverageUtilizationRate": 29,
            "medianUtilizationRate": 30
          },
          "20": {
            "averageUtilizationRate": 23,
            "weightedAverageUtilizationRate": 23,
            "medianUtilizationRate": 22
          },
          "21": {
            "averageUtilizationRate": 9,
            "weightedAverageUtilizationRate": 10,
            "medianUtilizationRate": 9
          }
        }
      }
    }
  }
}
